{
  "best_global_step": null,
  "best_metric": null,
  "best_model_checkpoint": null,
  "epoch": 3.0,
  "eval_steps": 500,
  "global_step": 537,
  "is_hyper_param_search": false,
  "is_local_process_zero": true,
  "is_world_process_zero": true,
  "log_history": [
    {
      "epoch": 0.055865921787709494,
      "grad_norm": 11.360199928283691,
      "learning_rate": 1.9664804469273745e-05,
      "loss": 0.7418,
      "step": 10
    },
    {
      "epoch": 0.11173184357541899,
      "grad_norm": 2.6416871547698975,
      "learning_rate": 1.9292364990689013e-05,
      "loss": 0.7057,
      "step": 20
    },
    {
      "epoch": 0.16759776536312848,
      "grad_norm": 2.01847243309021,
      "learning_rate": 1.8919925512104285e-05,
      "loss": 0.6876,
      "step": 30
    },
    {
      "epoch": 0.22346368715083798,
      "grad_norm": 6.623424530029297,
      "learning_rate": 1.8547486033519553e-05,
      "loss": 0.6673,
      "step": 40
    },
    {
      "epoch": 0.27932960893854747,
      "grad_norm": 3.0960617065429688,
      "learning_rate": 1.8175046554934825e-05,
      "loss": 0.652,
      "step": 50
    },
    {
      "epoch": 0.33519553072625696,
      "grad_norm": 2.2838222980499268,
      "learning_rate": 1.7802607076350093e-05,
      "loss": 0.6486,
      "step": 60
    },
    {
      "epoch": 0.39106145251396646,
      "grad_norm": 4.236813068389893,
      "learning_rate": 1.7430167597765365e-05,
      "loss": 0.6383,
      "step": 70
    },
    {
      "epoch": 0.44692737430167595,
      "grad_norm": 10.501160621643066,
      "learning_rate": 1.7057728119180633e-05,
      "loss": 0.589,
      "step": 80
    },
    {
      "epoch": 0.5027932960893855,
      "grad_norm": 7.31002950668335,
      "learning_rate": 1.6685288640595905e-05,
      "loss": 0.6384,
      "step": 90
    },
    {
      "epoch": 0.5586592178770949,
      "grad_norm": 5.1201958656311035,
      "learning_rate": 1.6312849162011177e-05,
      "loss": 0.6572,
      "step": 100
    },
    {
      "epoch": 0.6145251396648045,
      "grad_norm": 5.8737711906433105,
      "learning_rate": 1.5940409683426445e-05,
      "loss": 0.6121,
      "step": 110
    },
    {
      "epoch": 0.6703910614525139,
      "grad_norm": 7.5602827072143555,
      "learning_rate": 1.5567970204841713e-05,
      "loss": 0.606,
      "step": 120
    },
    {
      "epoch": 0.7262569832402235,
      "grad_norm": 4.078781604766846,
      "learning_rate": 1.5195530726256983e-05,
      "loss": 0.6445,
      "step": 130
    },
    {
      "epoch": 0.7821229050279329,
      "grad_norm": 5.333395957946777,
      "learning_rate": 1.4823091247672255e-05,
      "loss": 0.6318,
      "step": 140
    },
    {
      "epoch": 0.8379888268156425,
      "grad_norm": 6.774143218994141,
      "learning_rate": 1.4450651769087525e-05,
      "loss": 0.6713,
      "step": 150
    },
    {
      "epoch": 0.8938547486033519,
      "grad_norm": 5.248743534088135,
      "learning_rate": 1.4078212290502795e-05,
      "loss": 0.6147,
      "step": 160
    },
    {
      "epoch": 0.9497206703910615,
      "grad_norm": 4.439449310302734,
      "learning_rate": 1.3705772811918065e-05,
      "loss": 0.6045,
      "step": 170
    },
    {
      "epoch": 1.0,
      "eval_accuracy": 0.6324607329842932,
      "eval_f1": 0.663470757430489,
      "eval_loss": 0.627109706401825,
      "eval_runtime": 13.0247,
      "eval_samples_per_second": 73.322,
      "eval_steps_per_second": 4.607,
      "step": 179
    },
    {
      "epoch": 1.005586592178771,
      "grad_norm": 7.518741607666016,
      "learning_rate": 1.3333333333333333e-05,
      "loss": 0.5962,
      "step": 180
    },
    {
      "epoch": 1.0614525139664805,
      "grad_norm": 4.056912899017334,
      "learning_rate": 1.2960893854748603e-05,
      "loss": 0.4194,
      "step": 190
    },
    {
      "epoch": 1.1173184357541899,
      "grad_norm": 8.32674503326416,
      "learning_rate": 1.2588454376163875e-05,
      "loss": 0.4692,
      "step": 200
    },
    {
      "epoch": 1.1731843575418994,
      "grad_norm": 6.8397722244262695,
      "learning_rate": 1.2216014897579145e-05,
      "loss": 0.5071,
      "step": 210
    },
    {
      "epoch": 1.229050279329609,
      "grad_norm": 7.906406402587891,
      "learning_rate": 1.1843575418994415e-05,
      "loss": 0.4784,
      "step": 220
    },
    {
      "epoch": 1.2849162011173183,
      "grad_norm": 5.2690887451171875,
      "learning_rate": 1.1471135940409683e-05,
      "loss": 0.4771,
      "step": 230
    },
    {
      "epoch": 1.3407821229050279,
      "grad_norm": 6.81321907043457,
      "learning_rate": 1.1098696461824953e-05,
      "loss": 0.4675,
      "step": 240
    },
    {
      "epoch": 1.3966480446927374,
      "grad_norm": 6.511667251586914,
      "learning_rate": 1.0726256983240225e-05,
      "loss": 0.4844,
      "step": 250
    },
    {
      "epoch": 1.452513966480447,
      "grad_norm": 8.852395057678223,
      "learning_rate": 1.0353817504655495e-05,
      "loss": 0.4636,
      "step": 260
    },
    {
      "epoch": 1.5083798882681565,
      "grad_norm": 12.283036231994629,
      "learning_rate": 9.981378026070763e-06,
      "loss": 0.5074,
      "step": 270
    },
    {
      "epoch": 1.564245810055866,
      "grad_norm": 9.509391784667969,
      "learning_rate": 9.608938547486035e-06,
      "loss": 0.5696,
      "step": 280
    },
    {
      "epoch": 1.6201117318435754,
      "grad_norm": 8.137529373168945,
      "learning_rate": 9.236499068901305e-06,
      "loss": 0.4155,
      "step": 290
    },
    {
      "epoch": 1.675977653631285,
      "grad_norm": 8.588197708129883,
      "learning_rate": 8.864059590316573e-06,
      "loss": 0.5311,
      "step": 300
    },
    {
      "epoch": 1.7318435754189943,
      "grad_norm": 5.654857158660889,
      "learning_rate": 8.491620111731845e-06,
      "loss": 0.4306,
      "step": 310
    },
    {
      "epoch": 1.7877094972067038,
      "grad_norm": 18.24455451965332,
      "learning_rate": 8.119180633147115e-06,
      "loss": 0.5131,
      "step": 320
    },
    {
      "epoch": 1.8435754189944134,
      "grad_norm": 12.005803108215332,
      "learning_rate": 7.746741154562383e-06,
      "loss": 0.4909,
      "step": 330
    },
    {
      "epoch": 1.899441340782123,
      "grad_norm": 7.37032413482666,
      "learning_rate": 7.374301675977654e-06,
      "loss": 0.4529,
      "step": 340
    },
    {
      "epoch": 1.9553072625698324,
      "grad_norm": 8.935149192810059,
      "learning_rate": 7.001862197392925e-06,
      "loss": 0.487,
      "step": 350
    },
    {
      "epoch": 2.0,
      "eval_accuracy": 0.6701570680628273,
      "eval_f1": 0.6749226006191951,
      "eval_loss": 0.6350603699684143,
      "eval_runtime": 17.8862,
      "eval_samples_per_second": 53.393,
      "eval_steps_per_second": 3.355,
      "step": 358
    },
    {
      "epoch": 2.011173184357542,
      "grad_norm": 6.8643293380737305,
      "learning_rate": 6.629422718808194e-06,
      "loss": 0.4316,
      "step": 360
    },
    {
      "epoch": 2.0670391061452515,
      "grad_norm": 9.84553337097168,
      "learning_rate": 6.256983240223464e-06,
      "loss": 0.2931,
      "step": 370
    },
    {
      "epoch": 2.122905027932961,
      "grad_norm": 10.677969932556152,
      "learning_rate": 5.884543761638735e-06,
      "loss": 0.3355,
      "step": 380
    },
    {
      "epoch": 2.17877094972067,
      "grad_norm": 6.948695659637451,
      "learning_rate": 5.512104283054004e-06,
      "loss": 0.3201,
      "step": 390
    },
    {
      "epoch": 2.2346368715083798,
      "grad_norm": 4.346865177154541,
      "learning_rate": 5.139664804469274e-06,
      "loss": 0.3676,
      "step": 400
    },
    {
      "epoch": 2.2905027932960893,
      "grad_norm": 9.627240180969238,
      "learning_rate": 4.767225325884544e-06,
      "loss": 0.3275,
      "step": 410
    },
    {
      "epoch": 2.346368715083799,
      "grad_norm": 22.195449829101562,
      "learning_rate": 4.394785847299814e-06,
      "loss": 0.4198,
      "step": 420
    },
    {
      "epoch": 2.4022346368715084,
      "grad_norm": 4.18413782119751,
      "learning_rate": 4.022346368715084e-06,
      "loss": 0.2947,
      "step": 430
    },
    {
      "epoch": 2.458100558659218,
      "grad_norm": 8.299964904785156,
      "learning_rate": 3.6499068901303543e-06,
      "loss": 0.3565,
      "step": 440
    },
    {
      "epoch": 2.5139664804469275,
      "grad_norm": 15.239314079284668,
      "learning_rate": 3.277467411545624e-06,
      "loss": 0.4116,
      "step": 450
    },
    {
      "epoch": 2.5698324022346366,
      "grad_norm": 11.390498161315918,
      "learning_rate": 2.9050279329608943e-06,
      "loss": 0.3573,
      "step": 460
    },
    {
      "epoch": 2.6256983240223466,
      "grad_norm": 6.041446208953857,
      "learning_rate": 2.5325884543761643e-06,
      "loss": 0.3312,
      "step": 470
    },
    {
      "epoch": 2.6815642458100557,
      "grad_norm": 11.735084533691406,
      "learning_rate": 2.160148975791434e-06,
      "loss": 0.3499,
      "step": 480
    },
    {
      "epoch": 2.7374301675977653,
      "grad_norm": 4.684360504150391,
      "learning_rate": 1.787709497206704e-06,
      "loss": 0.3645,
      "step": 490
    },
    {
      "epoch": 2.793296089385475,
      "grad_norm": 13.067307472229004,
      "learning_rate": 1.4152700186219739e-06,
      "loss": 0.3257,
      "step": 500
    },
    {
      "epoch": 2.8491620111731844,
      "grad_norm": 8.811724662780762,
      "learning_rate": 1.042830540037244e-06,
      "loss": 0.3005,
      "step": 510
    },
    {
      "epoch": 2.905027932960894,
      "grad_norm": 14.606193542480469,
      "learning_rate": 6.703910614525141e-07,
      "loss": 0.3124,
      "step": 520
    },
    {
      "epoch": 2.9608938547486034,
      "grad_norm": 10.35899543762207,
      "learning_rate": 2.97951582867784e-07,
      "loss": 0.3534,
      "step": 530
    }
  ],
  "logging_steps": 10,
  "max_steps": 537,
  "num_input_tokens_seen": 0,
  "num_train_epochs": 3,
  "save_steps": 500,
  "stateful_callbacks": {
    "TrainerControl": {
      "args": {
        "should_epoch_stop": false,
        "should_evaluate": false,
        "should_log": false,
        "should_save": true,
        "should_training_stop": true
      },
      "attributes": {}
    }
  },
  "total_flos": 564767880330240.0,
  "train_batch_size": 16,
  "trial_name": null,
  "trial_params": null
}
